git_auto_deploy-0.2.1.dist-info/RECORD
git_auto_deploy-0.2.1.dist-info/entry_points.txt
git_auto_deploy-0.2.1.dist-info/WHEEL
git_auto_deploy-0.2.1.dist-info/METADATA
git_auto_deploy-0.2.1.dist-info/DESCRIPTION.rst
git_auto_deploy-0.2.1.dist-info/top_level.txt
git_auto_deploy-0.2.1.dist-info/metadata.json
gitautodeploy/__init__.py
gitautodeploy/lock.py
gitautodeploy/httpserver.py
gitautodeploy/__main__.py
gitautodeploy/gitautodeploy.py
gitautodeploy/parsers/github.py
gitautodeploy/parsers/__init__.py
gitautodeploy/parsers/common.py
gitautodeploy/parsers/gitlab.py
gitautodeploy/parsers/generic.py
gitautodeploy/parsers/bitbucket.py
gitautodeploy/parsers/gitlabci.py
gitautodeploy/cli/__init__.py
gitautodeploy/cli/config.py
gitautodeploy/wrappers/__init__.py
gitautodeploy/wrappers/git.py
gitautodeploy/wrappers/process.py
