Metadata-Version: 2.0
Name: git-auto-deploy
Version: 0.2.1
Summary: Deploy your GitHub, GitLab or Bitbucket projects automatically on Git push events or webhooks.
Home-page: https://github.com/olipo186/Git-Auto-Deploy
Author: Oliver Poignant
Author-email: oliver@poignant.se
License: UNKNOWN
Platform: UNKNOWN
